opentable_mcp_server.py
opentable_mcp_server-1.3.2.dist-info/METADATA
opentable_mcp_server-1.3.2.dist-info/WHEEL
opentable_mcp_server-1.3.2.dist-info/entry_points.txt
opentable_mcp_server-1.3.2.dist-info/top_level.txt
opentable_mcp_server-1.3.2.dist-info/RECORD
